pyckish/__init__.py
pyckish/basic_elements/__init__.py
pyckish/basic_elements/context.py
pyckish/basic_elements/context_element.py
pyckish/basic_elements/event.py
pyckish/basic_elements/event_element.py
pyckish/exceptions/validation_error.py
pyckish/http_elements/__init__.py
pyckish/http_elements/http_body.py
pyckish/http_elements/http_header.py
pyckish/http_elements/http_headers.py
pyckish/http_elements/http_method.py
pyckish/http_elements/http_path.py
pyckish/http_elements/http_path_parameter.py
pyckish/http_elements/http_path_parameters.py
pyckish/http_elements/http_query_parameter.py
pyckish/http_elements/http_query_parameters.py
pyckish/http_elements/http_response.py
pyckish/internal_handlers/exception_handler.py
pyckish/internal_handlers/interceptor_handler.py
pyckish/internal_handlers/parameter_handler.py
pyckish/internal_handlers/response_handler.py
pyckish/lambda_input_element.py
pyckish/main.py
pyckish/types/__init__.py
pyckish/types/http_codes.py
pyckish-0.7.5.dist-info/METADATA
pyckish-0.7.5.dist-info/WHEEL
pyckish-0.7.5.dist-info/RECORD
