Metadata-Version: 2.1
Name: pyckish
Version: 0.7.5
Summary: Pyckish is a micro framework for creating AWS Lambdas in Python in beautiful manner.
Author: Pedro Dardengo
Author-email: pedrodardengo@hotmail.com
Requires-Python: >=3.9,<3.10
Classifier: Programming Language :: Python :: 3
Classifier: Programming Language :: Python :: 3.9
Requires-Dist: pydantic (>=1.9,<2.0)
